easily_quiz
