Metadata-Version: 2.1
Name: easily-quiz
Version: 1.3
Summary: easily_quiz is a spanish api that you can create simple quiz!
Home-page: https://github.com/PinaYTTT/easily_quiz
Author: PinaYT
Author-email: contacto.pinayt@gmail.com
License: MIT
Download-URL: https://github.com/PinaYTTT/easily_quiz
Keywords: easily_quiz,quiz,truefalse
Platform: UNKNOWN
